[
    {
        "pnu": "1165010800113380005",
        "service_name": "GBD",
        "land_char_WFS": {
            "NSDI:PNU": "1165010800113380005",
            "gml:posList": "127.02974727 37.49010027 127.02951544 37.49003005 127.02959397 37.48986542 127.02982611 37.48993572 127.02974727 37.49010027",
            "NSDI:REGSTR_SE_CODE": "1",
            "NSDI:LNDCGR_CODE": "08",
            "NSDI:LNDCGR_CODE_NM": "대",
            "NSDI:LNDPCL_AR": "429.1",
            "NSDI:LAD_USE_SITTN": "210",
            "NSDI:LAD_USE_SITTN_NM": "상업용",
            "NSDI:TPGRPH_HG_CODE": "02",
            "NSDI:TPGRPH_HG_CODE_NM": "평지",
            "NSDI:TPGRPH_FRM_CODE": "02",
            "NSDI:TPGRPH_FRM_CODE_NM": "가로장방",
            "NSDI:ROAD_SIDE_CODE": "07",
            "NSDI:ROAD_SIDE_CODE_NM": "소로각지",
            "NSDI:FRST_REGIST_DT": "2021-08-11Z"
        },
        "land_own_WFS": {
            "NSDI:PNU": "1165010800113380005",
            "NSDI:POSESN_SE_CODE": "06",
            "NSDI:LBL": "법인",
            "NSDI:CNRS_PSN_CO": "1",
            "NSDI:AGRDE_SE_CODE": "11",
            "NSDI:RESDNC_SE_CODE": "ZZ",
            "NSDI:OWNSHIP_CHG_CAUSE_CODE": "03",
            "NSDI:OWNSHIP_CHG_DE": "20190430",
            "NSDI:NATION_INSTT_SE_CODE": "ZZ",
            "NSDI:FRST_REGIST_DT": "2021-09-12T03:00:57"
        },
        "land_price": {
            "NSDI:PNU": "1165010800113380005",
            "NSDI:PBLNTF_PCLND_STDR_YEAR": "2021",
            "NSDI:PBLNTF_PCLND_STDR_MT": "01",
            "NSDI:STD_LAND_AT": "0",
            "NSDI:PBLNTF_PCLND": "23320000",
            "NSDI:PSTYR_1_PBLNTF_PCLND": "21090000",
            "NSDI:PSTYR_2_PBLNTF_PCLND": "20240000",
            "NSDI:PSTYR_3_PBLNTF_PCLND": "18230000",
            "NSDI:PSTYR_4_PBLNTF_PCLND": "16960000",
            "NSDI:FRST_REGIST_DT": "2021-08-25T10:08:50"
        },
        "land_use_WFS": {
            "NSDI:PNU": "1165010800113380005",
            "NSDI:PRPOS_AREA_DSTRC_CODE_LIST": "UBA100,UDX200,UMZ100,UNE200,UOA120,UQA220,UQS100",
            "NSDI:PRPOS_AREA_DSTRC_NM_LIST": "과밀억제권역,가로구역별 최고높이 제한지역,가축사육제한구역,대공방어협조구역(위탁고도:77-257m),상대보호구역(2014-03-04),일반상업지역,도로(접합)",
            "NSDI:CNFLC_AT_LIST": "1,1,1,1,1,1,3",
            "NSDI:FRST_REGIST_DT": "2021-08-08T03:00:11"
        }
    },
    {
        "pnu": "1165010800113380006",
        "service_name": "GBD",
        "land_char_WFS": {
            "NSDI:PNU": "1165010800113380006",
            "gml:posList": "127.02982611 37.48993572 127.02959397 37.48986542 127.02969678 37.48965015 127.02974834 37.48963175 127.02994341 37.4896909 127.02982611 37.48993572",
            "NSDI:REGSTR_SE_CODE": "1",
            "NSDI:LNDCGR_CODE": "08",
            "NSDI:LNDCGR_CODE_NM": "대",
            "NSDI:LNDPCL_AR": "633.1",
            "NSDI:LAD_USE_SITTN": "210",
            "NSDI:LAD_USE_SITTN_NM": "상업용",
            "NSDI:TPGRPH_HG_CODE": "02",
            "NSDI:TPGRPH_HG_CODE_NM": "평지",
            "NSDI:TPGRPH_FRM_CODE": "02",
            "NSDI:TPGRPH_FRM_CODE_NM": "가로장방",
            "NSDI:ROAD_SIDE_CODE": "07",
            "NSDI:ROAD_SIDE_CODE_NM": "소로각지",
            "NSDI:FRST_REGIST_DT": "2021-08-11Z"
        },
        "land_own_WFS": {
            "NSDI:PNU": "1165010800113380006",
            "NSDI:POSESN_SE_CODE": "06",
            "NSDI:LBL": "법인",
            "NSDI:CNRS_PSN_CO": "1",
            "NSDI:AGRDE_SE_CODE": "11",
            "NSDI:RESDNC_SE_CODE": "ZZ",
            "NSDI:OWNSHIP_CHG_CAUSE_CODE": "03",
            "NSDI:OWNSHIP_CHG_DE": "20190430",
            "NSDI:NATION_INSTT_SE_CODE": "ZZ",
            "NSDI:FRST_REGIST_DT": "2021-09-12T03:00:57"
        },
        "land_price": {
            "NSDI:PNU": "1165010800113380006",
            "NSDI:PBLNTF_PCLND_STDR_YEAR": "2021",
            "NSDI:PBLNTF_PCLND_STDR_MT": "01",
            "NSDI:STD_LAND_AT": "0",
            "NSDI:PBLNTF_PCLND": "23320000",
            "NSDI:PSTYR_1_PBLNTF_PCLND": "21090000",
            "NSDI:PSTYR_2_PBLNTF_PCLND": "20240000",
            "NSDI:PSTYR_3_PBLNTF_PCLND": "18230000",
            "NSDI:PSTYR_4_PBLNTF_PCLND": "16960000",
            "NSDI:FRST_REGIST_DT": "2021-08-25T10:08:50"
        },
        "land_use_WFS": {
            "NSDI:PNU": "1165010800113380006",
            "NSDI:PRPOS_AREA_DSTRC_CODE_LIST": "UBA100,UDX200,UMZ100,UNE200,UOA120,UQA220,UQS100",
            "NSDI:PRPOS_AREA_DSTRC_NM_LIST": "과밀억제권역,가로구역별 최고높이 제한지역,가축사육제한구역,대공방어협조구역(위탁고도:77-257m),상대보호구역(2014-03-04),일반상업지역,도로(접합)",
            "NSDI:CNFLC_AT_LIST": "1,1,1,1,1,1,3",
            "NSDI:FRST_REGIST_DT": "2021-08-08T03:00:11"
        }
    },
    {
        "pnu": "1165010800113380007",
        "service_name": "GBD",
        "land_char_WFS": {
            "NSDI:PNU": "1165010800113380007",
            "gml:posList": "127.02995728 37.49016389 127.02974727 37.49010027 127.02982611 37.48993572 127.02994341 37.4896909 127.03015647 37.48975545 127.0300419 37.48999533 127.03025507 37.49005997 127.03017409 37.49022956 127.02995728 37.49016389",
            "NSDI:REGSTR_SE_CODE": "1",
            "NSDI:LNDCGR_CODE": "08",
            "NSDI:LNDCGR_CODE_NM": "대",
            "NSDI:LNDPCL_AR": "1387.9",
            "NSDI:LAD_USE_SITTN": "230",
            "NSDI:LAD_USE_SITTN_NM": "상업나지",
            "NSDI:TPGRPH_HG_CODE": "02",
            "NSDI:TPGRPH_HG_CODE_NM": "평지",
            "NSDI:TPGRPH_FRM_CODE": "04",
            "NSDI:TPGRPH_FRM_CODE_NM": "사다리형",
            "NSDI:ROAD_SIDE_CODE": "07",
            "NSDI:ROAD_SIDE_CODE_NM": "소로각지",
            "NSDI:FRST_REGIST_DT": "2021-08-11Z"
        },
        "land_own_WFS": {
            "NSDI:PNU": "1165010800113380007",
            "NSDI:POSESN_SE_CODE": "06",
            "NSDI:LBL": "법인",
            "NSDI:CNRS_PSN_CO": "1",
            "NSDI:AGRDE_SE_CODE": "11",
            "NSDI:RESDNC_SE_CODE": "ZZ",
            "NSDI:OWNSHIP_CHG_CAUSE_CODE": "03",
            "NSDI:OWNSHIP_CHG_DE": "20190430",
            "NSDI:NATION_INSTT_SE_CODE": "ZZ",
            "NSDI:FRST_REGIST_DT": "2021-09-12T03:00:57"
        },
        "land_price": {
            "NSDI:PNU": "1165010800113380007",
            "NSDI:PBLNTF_PCLND_STDR_YEAR": "2021",
            "NSDI:PBLNTF_PCLND_STDR_MT": "01",
            "NSDI:STD_LAND_AT": "0",
            "NSDI:PBLNTF_PCLND": "21670000",
            "NSDI:PSTYR_1_PBLNTF_PCLND": "19600000",
            "NSDI:PSTYR_2_PBLNTF_PCLND": "18810000",
            "NSDI:PSTYR_3_PBLNTF_PCLND": "17130000",
            "NSDI:PSTYR_4_PBLNTF_PCLND": "13200000",
            "NSDI:FRST_REGIST_DT": "2021-08-25T10:08:50"
        },
        "land_use_WFS": {
            "NSDI:PNU": "1165010800113380007",
            "NSDI:PRPOS_AREA_DSTRC_CODE_LIST": "UBA100,UDX200,UMZ100,UNE200,UOA120,UQA220",
            "NSDI:PRPOS_AREA_DSTRC_NM_LIST": "과밀억제권역,가로구역별 최고높이 제한지역,가축사육제한구역,대공방어협조구역(위탁고도:77-257m),상대보호구역(2014-03-04),일반상업지역",
            "NSDI:CNFLC_AT_LIST": "1,1,1,1,1,1",
            "NSDI:FRST_REGIST_DT": "2021-08-08T03:00:11"
        }
    },
    {
        "pnu": "1165010800113390000",
        "service_name": "GBD",
        "land_char_WFS": {
            "NSDI:PNU": "1165010800113390000",
            "gml:posList": "127.02990075 37.48960081 127.02978054 37.48956435 127.02975734 37.48952327 127.02981847 37.48939541 127.02997606 37.4894431 127.02990075 37.48960081",
            "NSDI:REGSTR_SE_CODE": "1",
            "NSDI:LNDCGR_CODE": "08",
            "NSDI:LNDCGR_CODE_NM": "대",
            "NSDI:LNDPCL_AR": "273",
            "NSDI:LAD_USE_SITTN": "220",
            "NSDI:LAD_USE_SITTN_NM": "업무용",
            "NSDI:TPGRPH_HG_CODE": "02",
            "NSDI:TPGRPH_HG_CODE_NM": "평지",
            "NSDI:TPGRPH_FRM_CODE": "02",
            "NSDI:TPGRPH_FRM_CODE_NM": "가로장방",
            "NSDI:ROAD_SIDE_CODE": "07",
            "NSDI:ROAD_SIDE_CODE_NM": "소로각지",
            "NSDI:FRST_REGIST_DT": "2021-08-11Z"
        },
        "land_own_WFS": {
            "NSDI:PNU": "1165010800113390000",
            "NSDI:POSESN_SE_CODE": {
                "@xsi:nil": "true"
            },
            "NSDI:LBL": "집합건물",
            "NSDI:CNRS_PSN_CO": "84",
            "NSDI:AGRDE_SE_CODE": {
                "@xsi:nil": "true"
            },
            "NSDI:RESDNC_SE_CODE": {
                "@xsi:nil": "true"
            },
            "NSDI:OWNSHIP_CHG_CAUSE_CODE": {
                "@xsi:nil": "true"
            },
            "NSDI:OWNSHIP_CHG_DE": {
                "@xsi:nil": "true"
            },
            "NSDI:NATION_INSTT_SE_CODE": {
                "@xsi:nil": "true"
            },
            "NSDI:FRST_REGIST_DT": "2021-09-12T03:00:57"
        },
        "land_price": {
            "NSDI:PNU": "1165010800113390000",
            "NSDI:PBLNTF_PCLND_STDR_YEAR": "2021",
            "NSDI:PBLNTF_PCLND_STDR_MT": "01",
            "NSDI:STD_LAND_AT": "0",
            "NSDI:PBLNTF_PCLND": "23320000",
            "NSDI:PSTYR_1_PBLNTF_PCLND": "21090000",
            "NSDI:PSTYR_2_PBLNTF_PCLND": "20240000",
            "NSDI:PSTYR_3_PBLNTF_PCLND": "18230000",
            "NSDI:PSTYR_4_PBLNTF_PCLND": "16920000",
            "NSDI:FRST_REGIST_DT": "2021-08-25T10:08:50"
        },
        "land_use_WFS": {
            "NSDI:PNU": "1165010800113390000",
            "NSDI:PRPOS_AREA_DSTRC_CODE_LIST": "UBA100,UDX200,UMZ100,UNE200,UOA120,UQA220,UQS100",
            "NSDI:PRPOS_AREA_DSTRC_NM_LIST": "과밀억제권역,가로구역별 최고높이 제한지역,가축사육제한구역,대공방어협조구역(위탁고도:77-257m),상대보호구역(2014-03-04),일반상업지역,도로(접합)",
            "NSDI:CNFLC_AT_LIST": "1,1,1,1,1,1,3",
            "NSDI:FRST_REGIST_DT": "2021-08-08T03:00:11"
        }
    },
    {
        "pnu": "1165010800113390001",
        "service_name": "GBD",
        "land_char_WFS": {
            "NSDI:PNU": "1165010800113390001",
            "gml:posList": "127.02990075 37.48960081 127.02997606 37.4894431 127.03007847 37.48922866 127.0303527 37.48931283 127.03017544 37.48968409 127.02990075 37.48960081",
            "NSDI:REGSTR_SE_CODE": "1",
            "NSDI:LNDCGR_CODE": "08",
            "NSDI:LNDCGR_CODE_NM": "대",
            "NSDI:LNDPCL_AR": "1147.3",
            "NSDI:LAD_USE_SITTN": "210",
            "NSDI:LAD_USE_SITTN_NM": "상업용",
            "NSDI:TPGRPH_HG_CODE": "02",
            "NSDI:TPGRPH_HG_CODE_NM": "평지",
            "NSDI:TPGRPH_FRM_CODE": "03",
            "NSDI:TPGRPH_FRM_CODE_NM": "세로장방",
            "NSDI:ROAD_SIDE_CODE": "02",
            "NSDI:ROAD_SIDE_CODE_NM": "광대소각",
            "NSDI:FRST_REGIST_DT": "2021-08-11Z"
        },
        "land_own_WFS": {
            "NSDI:PNU": "1165010800113390001",
            "NSDI:POSESN_SE_CODE": "06",
            "NSDI:LBL": "법인",
            "NSDI:CNRS_PSN_CO": "1",
            "NSDI:AGRDE_SE_CODE": "ZZ",
            "NSDI:RESDNC_SE_CODE": "ZZ",
            "NSDI:OWNSHIP_CHG_CAUSE_CODE": "03",
            "NSDI:OWNSHIP_CHG_DE": "20170424",
            "NSDI:NATION_INSTT_SE_CODE": "ZZ",
            "NSDI:FRST_REGIST_DT": "2021-09-12T03:00:57"
        },
        "land_price": {
            "NSDI:PNU": "1165010800113390001",
            "NSDI:PBLNTF_PCLND_STDR_YEAR": "2021",
            "NSDI:PBLNTF_PCLND_STDR_MT": "01",
            "NSDI:STD_LAND_AT": "1",
            "NSDI:PBLNTF_PCLND": "30650000",
            "NSDI:PSTYR_1_PBLNTF_PCLND": "29000000",
            "NSDI:PSTYR_2_PBLNTF_PCLND": "26600000",
            "NSDI:PSTYR_3_PBLNTF_PCLND": "23080000",
            "NSDI:PSTYR_4_PBLNTF_PCLND": "21430000",
            "NSDI:FRST_REGIST_DT": "2021-08-25T10:08:50"
        },
        "land_use_WFS": {
            "NSDI:PNU": "1165010800113390001",
            "NSDI:PRPOS_AREA_DSTRC_CODE_LIST": "UBA100,UDX200,UMZ100,UNE200,UOA120,UQA220,ZA0013",
            "NSDI:PRPOS_AREA_DSTRC_NM_LIST": "과밀억제권역,가로구역별 최고높이 제한지역,가축사육제한구역,대공방어협조구역(위탁고도:77-257m),상대보호구역(2014-03-04),일반상업지역,건축선(도로경계선에서 3m후퇴)",
            "NSDI:CNFLC_AT_LIST": "1,1,1,1,1,1,2",
            "NSDI:FRST_REGIST_DT": "2021-08-08T03:00:11"
        }
    },
    {
        "pnu": "1165010800113390002",
        "service_name": "GBD",
        "land_char_WFS": {
            "NSDI:PNU": "1165010800113390002",
            "gml:posList": "127.02997606 37.4894431 127.02981847 37.48939541 127.02992117 37.4891804 127.03007847 37.48922866 127.02997606 37.4894431",
            "NSDI:REGSTR_SE_CODE": "1",
            "NSDI:LNDCGR_CODE": "08",
            "NSDI:LNDCGR_CODE_NM": "대",
            "NSDI:LNDPCL_AR": "380.2",
            "NSDI:LAD_USE_SITTN": "210",
            "NSDI:LAD_USE_SITTN_NM": "상업용",
            "NSDI:TPGRPH_HG_CODE": "02",
            "NSDI:TPGRPH_HG_CODE_NM": "평지",
            "NSDI:TPGRPH_FRM_CODE": "03",
            "NSDI:TPGRPH_FRM_CODE_NM": "세로장방",
            "NSDI:ROAD_SIDE_CODE": "02",
            "NSDI:ROAD_SIDE_CODE_NM": "광대소각",
            "NSDI:FRST_REGIST_DT": "2021-08-11Z"
        },
        "land_own_WFS": {
            "NSDI:PNU": "1165010800113390002",
            "NSDI:POSESN_SE_CODE": {
                "@xsi:nil": "true"
            },
            "NSDI:LBL": "공유지",
            "NSDI:CNRS_PSN_CO": "3",
            "NSDI:AGRDE_SE_CODE": {
                "@xsi:nil": "true"
            },
            "NSDI:RESDNC_SE_CODE": {
                "@xsi:nil": "true"
            },
            "NSDI:OWNSHIP_CHG_CAUSE_CODE": {
                "@xsi:nil": "true"
            },
            "NSDI:OWNSHIP_CHG_DE": {
                "@xsi:nil": "true"
            },
            "NSDI:NATION_INSTT_SE_CODE": {
                "@xsi:nil": "true"
            },
            "NSDI:FRST_REGIST_DT": "2021-09-12T03:00:57"
        },
        "land_price": {
            "NSDI:PNU": "1165010800113390002",
            "NSDI:PBLNTF_PCLND_STDR_YEAR": "2021",
            "NSDI:PBLNTF_PCLND_STDR_MT": "01",
            "NSDI:STD_LAND_AT": "0",
            "NSDI:PBLNTF_PCLND": "30650000",
            "NSDI:PSTYR_1_PBLNTF_PCLND": "29000000",
            "NSDI:PSTYR_2_PBLNTF_PCLND": "26600000",
            "NSDI:PSTYR_3_PBLNTF_PCLND": "23080000",
            "NSDI:PSTYR_4_PBLNTF_PCLND": "21430000",
            "NSDI:FRST_REGIST_DT": "2021-08-25T10:08:50"
        },
        "land_use_WFS": {
            "NSDI:PNU": "1165010800113390002",
            "NSDI:PRPOS_AREA_DSTRC_CODE_LIST": "UBA100,UDX200,UMZ100,UNE200,UOA120,UQA220,UQS100,ZA0013",
            "NSDI:PRPOS_AREA_DSTRC_NM_LIST": "과밀억제권역,가로구역별 최고높이 제한지역,가축사육제한구역,대공방어협조구역(위탁고도:77-257m),상대보호구역(2014-03-04),일반상업지역,도로(접합),건축선(도로경계선에서 3m후퇴)",
            "NSDI:CNFLC_AT_LIST": "1,1,1,1,1,1,3,2",
            "NSDI:FRST_REGIST_DT": "2021-08-08T03:00:11"
        }
    }
]